openlayers/__init__.py
openlayers/abstracts.py
openlayers/anywidget.py
openlayers/basemaps.py
openlayers/colors.py
openlayers/config.py
openlayers/constants.py
openlayers/controls.py
openlayers/export.py
openlayers/express.py
openlayers/formats.py
openlayers/geopandas.py
openlayers/layers.py
openlayers/map.py
openlayers/map_options.py
openlayers/sources.py
openlayers/styles.py
openlayers/templates.py
openlayers/utils.py
openlayers/view.py
openlayers/__future__/__init__.py
openlayers/__future__/datasets.py
openlayers/__future__/elements.py
openlayers/__future__/sources.py
openlayers/js/openlayers.anywidget.css
openlayers/js/openlayers.anywidget.dev.css
openlayers/js/openlayers.anywidget.dev.js
openlayers/js/openlayers.anywidget.js
openlayers/js/openlayers.standalone.css
openlayers/js/openlayers.standalone.js
openlayers/models/__init__.py
openlayers/models/controls.py
openlayers/models/core.py
openlayers/models/formats.py
openlayers/models/layers.py
openlayers/models/map_options.py
openlayers/models/sources.py
openlayers/models/view.py
openlayers-0.1.6.dist-info/METADATA
openlayers-0.1.6.dist-info/WHEEL
openlayers-0.1.6.dist-info/licenses/LICENSE.md
openlayers-0.1.6.dist-info/RECORD
