Metadata-Version: 2.4
Name: openlayers
Version: 0.1.6
Summary: Python Bindings for OpenLayersJS
Author-email: Stefan Kuethe <stefan.kuethe@eoda.de>
License-File: LICENSE.md
Requires-Python: <4,>=3.10
Requires-Dist: anywidget>=0.9.0
Requires-Dist: eval-type-backport>=0.2.2
Requires-Dist: jinja2>=3.1.6
Requires-Dist: pydantic>=2.5.3
Requires-Dist: pyproj>=3.6.1
